{
  "cookies": [
    {
      "name": "session-username",
      "value": "standard_user",
      "domain": "www.saucedemo.com",
      "path": "/",
      "expires": 1782120469,
      "httpOnly": false,
      "secure": false,
      "sameSite": "Lax"
    }
  ],
  "origins": [
    {
      "origin": "https://www.saucedemo.com",
      "localStorage": [
        {
          "name": "backtrace-guid",
          "value": "32073c9f-1971-4764-b4de-88c103fb2755"
        },
        {
          "name": "backtrace-last-active",
          "value": "1782119868886"
        }
      ]
    }
  ]
}